LICENSE.rst
LICENSE_GPL.rst
MANIFEST.in
README.rst
setup.py
src/agx/__init__.py
src/agx.generator.buildout.egg-info/PKG-INFO
src/agx.generator.buildout.egg-info/SOURCES.txt
src/agx.generator.buildout.egg-info/dependency_links.txt
src/agx.generator.buildout.egg-info/entry_points.txt
src/agx.generator.buildout.egg-info/namespace_packages.txt
src/agx.generator.buildout.egg-info/not-zip-safe
src/agx.generator.buildout.egg-info/requires.txt
src/agx.generator.buildout.egg-info/top_level.txt
src/agx/generator/__init__.py
src/agx/generator/buildout/__init__.py
src/agx/generator/buildout/configure.zcml
src/agx/generator/buildout/generator.rst
src/agx/generator/buildout/plone_self_contained.py
src/agx/generator/buildout/profiles.py
src/agx/generator/buildout/tests.py
src/agx/generator/buildout/profiles/buildout.profile.di
src/agx/generator/buildout/profiles/buildout.profile.notation
src/agx/generator/buildout/profiles/buildout.profile.uml
src/agx/generator/buildout/templates/bootstrap.py.jinja
src/agx/generator/buildout/templates/buildout.cfg.jinja
src/agx/generator/buildout/testing/__init__.py
src/agx/generator/buildout/testing/data/agx.generator.buildout-sample.di
src/agx/generator/buildout/testing/data/agx.generator.buildout-sample.notation
src/agx/generator/buildout/testing/data/agx.generator.buildout-sample.uml
src/agx/generator/buildout/testing/data/agx.generator.buildout-sample/LICENSE.rst
src/agx/generator/buildout/testing/data/agx.generator.buildout-sample/MANIFEST.rst
src/agx/generator/buildout/testing/data/agx.generator.buildout-sample/README.rst
src/agx/generator/buildout/testing/data/agx.generator.buildout-sample/bootstrap.py
src/agx/generator/buildout/testing/data/agx.generator.buildout-sample/buildout.cfg
src/agx/generator/buildout/testing/data/agx.generator.buildout-sample/setup.py
src/agx/generator/buildout/testing/data/agx.generator.buildout-sample/src/agx/__init__.py
src/agx/generator/buildout/testing/data/agx.generator.buildout-sample/src/agx/testpackage/__init__.py